Metadata-Version: 2.1
Name: insurancecalculatorpackage
Version: 1.0.0
Summary: A small python library for calculating insurance premiums with my logic.
Author: Om Khulbe
Author-email: omkhulbe53@gmail.com
Classifier: Programming Language :: Python :: 3
Classifier: License :: OSI Approved :: MIT License
Classifier: Operating System :: OS Independent
Requires-Python: >=3.6
